shell2http.py
shell2http-2.10.dist-info/LICENSE
shell2http-2.10.dist-info/METADATA
shell2http-2.10.dist-info/WHEEL
shell2http-2.10.dist-info/entry_points.txt
shell2http-2.10.dist-info/top_level.txt
shell2http-2.10.dist-info/RECORD
