Metadata-Version: 2.1
Name: shell2http
Version: 2.10
Summary: Executing shell commands via HTTP server
Home-page: https://github.com/GitHub30/shell2http
Author: Tomofumi Inoue
Author-email: funaox@gmail.com
License: MIT
Project-URL: Bug Tracker, https://github.com/GitHub30/shell2http/issues
Keywords: shell2http subprocess python
Platform: any
Classifier: Environment :: Web Environment
Classifier: Intended Audience :: Developers
Classifier: Operating System :: OS Independent
Classifier: Programming Language :: Python :: 3
Classifier: Programming Language :: Python :: 3.6
Classifier: Programming Language :: Python :: 3.7
Classifier: Programming Language :: Python :: 3.8
Classifier: Programming Language :: Python :: 3.9
Classifier: Programming Language :: Python :: 3.10
Classifier: Programming Language :: Python :: 3.11
Classifier: Programming Language :: Python :: 3.12
Classifier: License :: OSI Approved :: MIT License
Classifier: Topic :: Utilities
Classifier: Topic :: Internet :: WWW/HTTP :: Dynamic Content
Classifier: Topic :: Software Development :: Libraries :: Python Modules
License-File: LICENSE
